nigeria_geodata/__init__.py
nigeria_geodata/async_core.py
nigeria_geodata/benchmark.py
nigeria_geodata/config.py
nigeria_geodata/core.py
nigeria_geodata/datasources/__init__.py
nigeria_geodata/datasources/base.py
nigeria_geodata/datasources/grid3.py
nigeria_geodata/models/__init__.py
nigeria_geodata/models/common.py
nigeria_geodata/utils/__init__.py
nigeria_geodata/utils/api.py
nigeria_geodata/utils/common.py
nigeria_geodata/utils/enums.py
nigeria_geodata/utils/exceptions.py
nigeria_geodata/utils/logger.py
nigeria_geodata-0.1.2.dist-info/LICENSE
nigeria_geodata-0.1.2.dist-info/METADATA
nigeria_geodata-0.1.2.dist-info/WHEEL
nigeria_geodata-0.1.2.dist-info/RECORD
